{
 "allow_copy": 0, 
 "allow_guest_to_view": 0, 
 "allow_import": 1, 
 "allow_rename": 0, 
 "autoname": "field:crop_name", 
 "beta": 0, 
 "creation": "2018-10-29 17:58:27.543719", 
 "custom": 0, 
 "docstatus": 0, 
 "doctype": "DocType", 
 "document_type": "Document", 
 "editable_grid": 1, 
 "engine": "InnoDB", 
 "fields": [
  {
   "allow_bulk_edit": 0, 
   "allow_on_submit": 0, 
   "bold": 0, 
   "collapsible": 0, 
   "columns": 0, 
   "fieldname": "operational_cost", 
   "fieldtype": "Section Break", 
   "hidden": 0, 
   "ignore_user_permissions": 0, 
   "ignore_xss_filter": 0, 
   "in_filter": 0, 
   "in_global_search": 0, 
   "in_list_view": 0, 
   "in_standard_filter": 0, 
   "label": "Operational Cost", 
   "length": 0, 
   "no_copy": 0, 
   "permlevel": 0, 
   "precision": "", 
   "print_hide": 0, 
   "print_hide_if_no_value": 0, 
   "read_only": 0, 
   "remember_last_selected_value": 0, 
   "report_hide": 0, 
   "reqd": 0, 
   "search_index": 0, 
   "set_only_once": 0, 
   "unique": 0
  }, 
  {
   "allow_bulk_edit": 0, 
   "allow_on_submit": 0, 
   "bold": 0, 
   "collapsible": 0, 
   "columns": 0, 
   "fieldname": "crop_name", 
   "fieldtype": "Select", 
   "hidden": 0, 
   "ignore_user_permissions": 0, 
   "ignore_xss_filter": 0, 
   "in_filter": 0, 
   "in_global_search": 0, 
   "in_list_view": 0, 
   "in_standard_filter": 0, 
   "label": "Crop Name", 
   "length": 0, 
   "no_copy": 0, 
   "options": "", 
   "permlevel": 0, 
   "precision": "", 
   "print_hide": 0, 
   "print_hide_if_no_value": 0, 
   "read_only": 0, 
   "remember_last_selected_value": 0, 
   "report_hide": 0, 
   "reqd": 0, 
   "search_index": 0, 
   "set_only_once": 0, 
   "unique": 0
  }, 
  {
   "allow_bulk_edit": 0, 
   "allow_on_submit": 0, 
   "bold": 0, 
   "collapsible": 0, 
   "columns": 0, 
   "fieldname": "column_break_4", 
   "fieldtype": "Column Break", 
   "hidden": 0, 
   "ignore_user_permissions": 0, 
   "ignore_xss_filter": 0, 
   "in_filter": 0, 
   "in_global_search": 0, 
   "in_list_view": 0, 
   "in_standard_filter": 0, 
   "length": 0, 
   "no_copy": 0, 
   "permlevel": 0, 
   "precision": "", 
   "print_hide": 0, 
   "print_hide_if_no_value": 0, 
   "read_only": 0, 
   "remember_last_selected_value": 0, 
   "report_hide": 0, 
   "reqd": 0, 
   "search_index": 0, 
   "set_only_once": 0, 
   "unique": 0
  }, 
  {
   "allow_bulk_edit": 0, 
   "allow_on_submit": 0, 
   "bold": 0, 
   "collapsible": 0, 
   "columns": 0, 
   "fieldname": "number_of_acres", 
   "fieldtype": "Float", 
   "hidden": 0, 
   "ignore_user_permissions": 0, 
   "ignore_xss_filter": 0, 
   "in_filter": 0, 
   "in_global_search": 0, 
   "in_list_view": 0, 
   "in_standard_filter": 0, 
   "label": "Number of Acres", 
   "length": 0, 
   "no_copy": 0, 
   "permlevel": 0, 
   "precision": "2", 
   "print_hide": 0, 
   "print_hide_if_no_value": 0, 
   "read_only": 0, 
   "remember_last_selected_value": 0, 
   "report_hide": 0, 
   "reqd": 0, 
   "search_index": 0, 
   "set_only_once": 0, 
   "unique": 0
  }, 
  {
   "allow_bulk_edit": 0, 
   "allow_on_submit": 0, 
   "bold": 0, 
   "collapsible": 0, 
   "columns": 0, 
   "fieldname": "human_labour", 
   "fieldtype": "Section Break", 
   "hidden": 0, 
   "ignore_user_permissions": 0, 
   "ignore_xss_filter": 0, 
   "in_filter": 0, 
   "in_global_search": 0, 
   "in_list_view": 0, 
   "in_standard_filter": 0, 
   "label": "Human Labour", 
   "length": 0, 
   "no_copy": 0, 
   "permlevel": 0, 
   "precision": "", 
   "print_hide": 0, 
   "print_hide_if_no_value": 0, 
   "read_only": 0, 
   "remember_last_selected_value": 0, 
   "report_hide": 0, 
   "reqd": 0, 
   "search_index": 0, 
   "set_only_once": 0, 
   "unique": 0
  }, 
  {
   "allow_bulk_edit": 0, 
   "allow_on_submit": 0, 
   "bold": 0, 
   "collapsible": 0, 
   "columns": 0, 
   "fieldname": "family", 
   "fieldtype": "Float", 
   "hidden": 0, 
   "ignore_user_permissions": 0, 
   "ignore_xss_filter": 0, 
   "in_filter": 0, 
   "in_global_search": 0, 
   "in_list_view": 0, 
   "in_standard_filter": 0, 
   "label": "Family", 
   "length": 0, 
   "no_copy": 0, 
   "permlevel": 0, 
   "precision": "2", 
   "print_hide": 0, 
   "print_hide_if_no_value": 0, 
   "read_only": 0, 
   "remember_last_selected_value": 0, 
   "report_hide": 0, 
   "reqd": 0, 
   "search_index": 0, 
   "set_only_once": 0, 
   "unique": 0
  }, 
  {
   "allow_bulk_edit": 0, 
   "allow_on_submit": 0, 
   "bold": 0, 
   "collapsible": 0, 
   "columns": 0, 
   "fieldname": "casual", 
   "fieldtype": "Float", 
   "hidden": 0, 
   "ignore_user_permissions": 0, 
   "ignore_xss_filter": 0, 
   "in_filter": 0, 
   "in_global_search": 0, 
   "in_list_view": 0, 
   "in_standard_filter": 0, 
   "label": "Casual", 
   "length": 0, 
   "no_copy": 0, 
   "permlevel": 0, 
   "precision": "2", 
   "print_hide": 0, 
   "print_hide_if_no_value": 0, 
   "read_only": 0, 
   "remember_last_selected_value": 0, 
   "report_hide": 0, 
   "reqd": 0, 
   "search_index": 0, 
   "set_only_once": 0, 
   "unique": 0
  }, 
  {
   "allow_bulk_edit": 0, 
   "allow_on_submit": 0, 
   "bold": 0, 
   "collapsible": 0, 
   "columns": 0, 
   "fieldname": "column_break_5", 
   "fieldtype": "Column Break", 
   "hidden": 0, 
   "ignore_user_permissions": 0, 
   "ignore_xss_filter": 0, 
   "in_filter": 0, 
   "in_global_search": 0, 
   "in_list_view": 0, 
   "in_standard_filter": 0, 
   "length": 0, 
   "no_copy": 0, 
   "permlevel": 0, 
   "precision": "", 
   "print_hide": 0, 
   "print_hide_if_no_value": 0, 
   "read_only": 0, 
   "remember_last_selected_value": 0, 
   "report_hide": 0, 
   "reqd": 0, 
   "search_index": 0, 
   "set_only_once": 0, 
   "unique": 0
  }, 
  {
   "allow_bulk_edit": 0, 
   "allow_on_submit": 0, 
   "bold": 0, 
   "collapsible": 0, 
   "columns": 0, 
   "fieldname": "attached", 
   "fieldtype": "Float", 
   "hidden": 0, 
   "ignore_user_permissions": 0, 
   "ignore_xss_filter": 0, 
   "in_filter": 0, 
   "in_global_search": 0, 
   "in_list_view": 0, 
   "in_standard_filter": 0, 
   "label": "Attached", 
   "length": 0, 
   "no_copy": 0, 
   "permlevel": 0, 
   "precision": "2", 
   "print_hide": 0, 
   "print_hide_if_no_value": 0, 
   "read_only": 0, 
   "remember_last_selected_value": 0, 
   "report_hide": 0, 
   "reqd": 0, 
   "search_index": 0, 
   "set_only_once": 0, 
   "unique": 0
  }, 
  {
   "allow_bulk_edit": 0, 
   "allow_on_submit": 0, 
   "bold": 0, 
   "collapsible": 0, 
   "columns": 0, 
   "fieldname": "human_labour_total", 
   "fieldtype": "Float", 
   "hidden": 0, 
   "ignore_user_permissions": 0, 
   "ignore_xss_filter": 0, 
   "in_filter": 0, 
   "in_global_search": 0, 
   "in_list_view": 0, 
   "in_standard_filter": 0, 
   "label": "Human Labour Total", 
   "length": 0, 
   "no_copy": 0, 
   "permlevel": 0, 
   "precision": "2", 
   "print_hide": 0, 
   "print_hide_if_no_value": 0, 
   "read_only": 1, 
   "remember_last_selected_value": 0, 
   "report_hide": 0, 
   "reqd": 0, 
   "search_index": 0, 
   "set_only_once": 0, 
   "unique": 0
  }, 
  {
   "allow_bulk_edit": 0, 
   "allow_on_submit": 0, 
   "bold": 0, 
   "collapsible": 0, 
   "columns": 0, 
   "fieldname": "bullock_labour", 
   "fieldtype": "Section Break", 
   "hidden": 0, 
   "ignore_user_permissions": 0, 
   "ignore_xss_filter": 0, 
   "in_filter": 0, 
   "in_global_search": 0, 
   "in_list_view": 0, 
   "in_standard_filter": 0, 
   "label": "Bullock Labour", 
   "length": 0, 
   "no_copy": 0, 
   "permlevel": 0, 
   "precision": "", 
   "print_hide": 0, 
   "print_hide_if_no_value": 0, 
   "read_only": 0, 
   "remember_last_selected_value": 0, 
   "report_hide": 0, 
   "reqd": 0, 
   "search_index": 0, 
   "set_only_once": 0, 
   "unique": 0
  }, 
  {
   "allow_bulk_edit": 0, 
   "allow_on_submit": 0, 
   "bold": 0, 
   "collapsible": 0, 
   "columns": 0, 
   "fieldname": "hired", 
   "fieldtype": "Float", 
   "hidden": 0, 
   "ignore_user_permissions": 0, 
   "ignore_xss_filter": 0, 
   "in_filter": 0, 
   "in_global_search": 0, 
   "in_list_view": 0, 
   "in_standard_filter": 0, 
   "label": "Hired", 
   "length": 0, 
   "no_copy": 0, 
   "permlevel": 0, 
   "precision": "2", 
   "print_hide": 0, 
   "print_hide_if_no_value": 0, 
   "read_only": 0, 
   "remember_last_selected_value": 0, 
   "report_hide": 0, 
   "reqd": 0, 
   "search_index": 0, 
   "set_only_once": 0, 
   "unique": 0
  }, 
  {
   "allow_bulk_edit": 0, 
   "allow_on_submit": 0, 
   "bold": 0, 
   "collapsible": 0, 
   "columns": 0, 
   "fieldname": "column_break_11", 
   "fieldtype": "Column Break", 
   "hidden": 0, 
   "ignore_user_permissions": 0, 
   "ignore_xss_filter": 0, 
   "in_filter": 0, 
   "in_global_search": 0, 
   "in_list_view": 0, 
   "in_standard_filter": 0, 
   "length": 0, 
   "no_copy": 0, 
   "permlevel": 0, 
   "precision": "", 
   "print_hide": 0, 
   "print_hide_if_no_value": 0, 
   "read_only": 0, 
   "remember_last_selected_value": 0, 
   "report_hide": 0, 
   "reqd": 0, 
   "search_index": 0, 
   "set_only_once": 0, 
   "unique": 0
  }, 
  {
   "allow_bulk_edit": 0, 
   "allow_on_submit": 0, 
   "bold": 0, 
   "collapsible": 0, 
   "columns": 0, 
   "fieldname": "owned", 
   "fieldtype": "Float", 
   "hidden": 0, 
   "ignore_user_permissions": 0, 
   "ignore_xss_filter": 0, 
   "in_filter": 0, 
   "in_global_search": 0, 
   "in_list_view": 0, 
   "in_standard_filter": 0, 
   "label": "Owned", 
   "length": 0, 
   "no_copy": 0, 
   "permlevel": 0, 
   "precision": "2", 
   "print_hide": 0, 
   "print_hide_if_no_value": 0, 
   "read_only": 0, 
   "remember_last_selected_value": 0, 
   "report_hide": 0, 
   "reqd": 0, 
   "search_index": 0, 
   "set_only_once": 0, 
   "unique": 0
  }, 
  {
   "allow_bulk_edit": 0, 
   "allow_on_submit": 0, 
   "bold": 0, 
   "collapsible": 0, 
   "columns": 0, 
   "fieldname": "bullock_labour_total", 
   "fieldtype": "Float", 
   "hidden": 0, 
   "ignore_user_permissions": 0, 
   "ignore_xss_filter": 0, 
   "in_filter": 0, 
   "in_global_search": 0, 
   "in_list_view": 0, 
   "in_standard_filter": 0, 
   "label": "Bullock Labour Total", 
   "length": 0, 
   "no_copy": 0, 
   "permlevel": 0, 
   "precision": "2", 
   "print_hide": 0, 
   "print_hide_if_no_value": 0, 
   "read_only": 1, 
   "remember_last_selected_value": 0, 
   "report_hide": 0, 
   "reqd": 0, 
   "search_index": 0, 
   "set_only_once": 0, 
   "unique": 0
  }, 
  {
   "allow_bulk_edit": 0, 
   "allow_on_submit": 0, 
   "bold": 0, 
   "collapsible": 0, 
   "columns": 0, 
   "fieldname": "machine_labour", 
   "fieldtype": "Section Break", 
   "hidden": 0, 
   "ignore_user_permissions": 0, 
   "ignore_xss_filter": 0, 
   "in_filter": 0, 
   "in_global_search": 0, 
   "in_list_view": 0, 
   "in_standard_filter": 0, 
   "label": "Machine Labour", 
   "length": 0, 
   "no_copy": 0, 
   "permlevel": 0, 
   "precision": "", 
   "print_hide": 0, 
   "print_hide_if_no_value": 0, 
   "read_only": 0, 
   "remember_last_selected_value": 0, 
   "report_hide": 0, 
   "reqd": 0, 
   "search_index": 0, 
   "set_only_once": 0, 
   "unique": 0
  }, 
  {
   "allow_bulk_edit": 0, 
   "allow_on_submit": 0, 
   "bold": 0, 
   "collapsible": 0, 
   "columns": 0, 
   "fieldname": "machine_hired", 
   "fieldtype": "Float", 
   "hidden": 0, 
   "ignore_user_permissions": 0, 
   "ignore_xss_filter": 0, 
   "in_filter": 0, 
   "in_global_search": 0, 
   "in_list_view": 0, 
   "in_standard_filter": 0, 
   "label": "Machine Hired", 
   "length": 0, 
   "no_copy": 0, 
   "permlevel": 0, 
   "precision": "2", 
   "print_hide": 0, 
   "print_hide_if_no_value": 0, 
   "read_only": 0, 
   "remember_last_selected_value": 0, 
   "report_hide": 0, 
   "reqd": 0, 
   "search_index": 0, 
   "set_only_once": 0, 
   "unique": 0
  }, 
  {
   "allow_bulk_edit": 0, 
   "allow_on_submit": 0, 
   "bold": 0, 
   "collapsible": 0, 
   "columns": 0, 
   "fieldname": "column_break_16", 
   "fieldtype": "Column Break", 
   "hidden": 0, 
   "ignore_user_permissions": 0, 
   "ignore_xss_filter": 0, 
   "in_filter": 0, 
   "in_global_search": 0, 
   "in_list_view": 0, 
   "in_standard_filter": 0, 
   "length": 0, 
   "no_copy": 0, 
   "permlevel": 0, 
   "precision": "", 
   "print_hide": 0, 
   "print_hide_if_no_value": 0, 
   "read_only": 0, 
   "remember_last_selected_value": 0, 
   "report_hide": 0, 
   "reqd": 0, 
   "search_index": 0, 
   "set_only_once": 0, 
   "unique": 0
  }, 
  {
   "allow_bulk_edit": 0, 
   "allow_on_submit": 0, 
   "bold": 0, 
   "collapsible": 0, 
   "columns": 0, 
   "fieldname": "machine_owned", 
   "fieldtype": "Float", 
   "hidden": 0, 
   "ignore_user_permissions": 0, 
   "ignore_xss_filter": 0, 
   "in_filter": 0, 
   "in_global_search": 0, 
   "in_list_view": 0, 
   "in_standard_filter": 0, 
   "label": "Machine Owned", 
   "length": 0, 
   "no_copy": 0, 
   "permlevel": 0, 
   "precision": "2", 
   "print_hide": 0, 
   "print_hide_if_no_value": 0, 
   "read_only": 0, 
   "remember_last_selected_value": 0, 
   "report_hide": 0, 
   "reqd": 0, 
   "search_index": 0, 
   "set_only_once": 0, 
   "unique": 0
  }, 
  {
   "allow_bulk_edit": 0, 
   "allow_on_submit": 0, 
   "bold": 0, 
   "collapsible": 0, 
   "columns": 0, 
   "fieldname": "machine_labour_total", 
   "fieldtype": "Float", 
   "hidden": 0, 
   "ignore_user_permissions": 0, 
   "ignore_xss_filter": 0, 
   "in_filter": 0, 
   "in_global_search": 0, 
   "in_list_view": 0, 
   "in_standard_filter": 0, 
   "label": "Machine Labour Total", 
   "length": 0, 
   "no_copy": 0, 
   "permlevel": 0, 
   "precision": "2", 
   "print_hide": 0, 
   "print_hide_if_no_value": 0, 
   "read_only": 1, 
   "remember_last_selected_value": 0, 
   "report_hide": 0, 
   "reqd": 0, 
   "search_index": 0, 
   "set_only_once": 0, 
   "unique": 0
  }, 
  {
   "allow_bulk_edit": 0, 
   "allow_on_submit": 0, 
   "bold": 0, 
   "collapsible": 0, 
   "columns": 0, 
   "fieldname": "seed_information", 
   "fieldtype": "Section Break", 
   "hidden": 0, 
   "ignore_user_permissions": 0, 
   "ignore_xss_filter": 0, 
   "in_filter": 0, 
   "in_global_search": 0, 
   "in_list_view": 0, 
   "in_standard_filter": 0, 
   "label": "Seed Information", 
   "length": 0, 
   "no_copy": 0, 
   "permlevel": 0, 
   "precision": "", 
   "print_hide": 0, 
   "print_hide_if_no_value": 0, 
   "read_only": 0, 
   "remember_last_selected_value": 0, 
   "report_hide": 0, 
   "reqd": 0, 
   "search_index": 0, 
   "set_only_once": 0, 
   "unique": 0
  }, 
  {
   "allow_bulk_edit": 0, 
   "allow_on_submit": 0, 
   "bold": 0, 
   "collapsible": 0, 
   "columns": 0, 
   "fieldname": "seed", 
   "fieldtype": "Table", 
   "hidden": 0, 
   "ignore_user_permissions": 0, 
   "ignore_xss_filter": 0, 
   "in_filter": 0, 
   "in_global_search": 0, 
   "in_list_view": 0, 
   "in_standard_filter": 0, 
   "label": "Seed", 
   "length": 0, 
   "no_copy": 0, 
   "options": "Seed Info", 
   "permlevel": 0, 
   "precision": "", 
   "print_hide": 0, 
   "print_hide_if_no_value": 0, 
   "read_only": 0, 
   "remember_last_selected_value": 0, 
   "report_hide": 0, 
   "reqd": 0, 
   "search_index": 0, 
   "set_only_once": 0, 
   "unique": 0
  }, 
  {
   "allow_bulk_edit": 0, 
   "allow_on_submit": 0, 
   "bold": 0, 
   "collapsible": 0, 
   "columns": 0, 
   "fieldname": "grand_total", 
   "fieldtype": "Float", 
   "hidden": 1, 
   "ignore_user_permissions": 0, 
   "ignore_xss_filter": 0, 
   "in_filter": 0, 
   "in_global_search": 0, 
   "in_list_view": 0, 
   "in_standard_filter": 0, 
   "label": "Grand Total", 
   "length": 0, 
   "no_copy": 1, 
   "options": "", 
   "permlevel": 0, 
   "print_hide": 1, 
   "print_hide_if_no_value": 0, 
   "read_only": 0, 
   "remember_last_selected_value": 0, 
   "report_hide": 0, 
   "reqd": 0, 
   "search_index": 0, 
   "set_only_once": 0, 
   "unique": 0
  }, 
  {
   "allow_bulk_edit": 0, 
   "allow_on_submit": 0, 
   "bold": 0, 
   "collapsible": 0, 
   "columns": 0, 
   "fieldname": "fertilizers_and_manures", 
   "fieldtype": "Section Break", 
   "hidden": 0, 
   "ignore_user_permissions": 0, 
   "ignore_xss_filter": 0, 
   "in_filter": 0, 
   "in_global_search": 0, 
   "in_list_view": 0, 
   "in_standard_filter": 0, 
   "label": "Fertilizers and Manures", 
   "length": 0, 
   "no_copy": 0, 
   "permlevel": 0, 
   "precision": "", 
   "print_hide": 0, 
   "print_hide_if_no_value": 0, 
   "read_only": 0, 
   "remember_last_selected_value": 0, 
   "report_hide": 0, 
   "reqd": 0, 
   "search_index": 0, 
   "set_only_once": 0, 
   "unique": 0
  }, 
  {
   "allow_bulk_edit": 0, 
   "allow_on_submit": 0, 
   "bold": 0, 
   "collapsible": 0, 
   "columns": 0, 
   "fieldname": "fertilizers", 
   "fieldtype": "Float", 
   "hidden": 0, 
   "ignore_user_permissions": 0, 
   "ignore_xss_filter": 0, 
   "in_filter": 0, 
   "in_global_search": 0, 
   "in_list_view": 0, 
   "in_standard_filter": 0, 
   "label": "Fertilizers", 
   "length": 0, 
   "no_copy": 0, 
   "permlevel": 0, 
   "precision": "2", 
   "print_hide": 0, 
   "print_hide_if_no_value": 0, 
   "read_only": 0, 
   "remember_last_selected_value": 0, 
   "report_hide": 0, 
   "reqd": 0, 
   "search_index": 0, 
   "set_only_once": 0, 
   "unique": 0
  }, 
  {
   "allow_bulk_edit": 0, 
   "allow_on_submit": 0, 
   "bold": 0, 
   "collapsible": 0, 
   "columns": 0, 
   "fieldname": "manures", 
   "fieldtype": "Float", 
   "hidden": 0, 
   "ignore_user_permissions": 0, 
   "ignore_xss_filter": 0, 
   "in_filter": 0, 
   "in_global_search": 0, 
   "in_list_view": 0, 
   "in_standard_filter": 0, 
   "label": "Manures", 
   "length": 0, 
   "no_copy": 0, 
   "permlevel": 0, 
   "precision": "2", 
   "print_hide": 0, 
   "print_hide_if_no_value": 0, 
   "read_only": 0, 
   "remember_last_selected_value": 0, 
   "report_hide": 0, 
   "reqd": 0, 
   "search_index": 0, 
   "set_only_once": 0, 
   "unique": 0
  }, 
  {
   "allow_bulk_edit": 0, 
   "allow_on_submit": 0, 
   "bold": 0, 
   "collapsible": 0, 
   "columns": 0, 
   "fieldname": "column_break_24", 
   "fieldtype": "Column Break", 
   "hidden": 0, 
   "ignore_user_permissions": 0, 
   "ignore_xss_filter": 0, 
   "in_filter": 0, 
   "in_global_search": 0, 
   "in_list_view": 0, 
   "in_standard_filter": 0, 
   "length": 0, 
   "no_copy": 0, 
   "permlevel": 0, 
   "precision": "", 
   "print_hide": 0, 
   "print_hide_if_no_value": 0, 
   "read_only": 0, 
   "remember_last_selected_value": 0, 
   "report_hide": 0, 
   "reqd": 0, 
   "search_index": 0, 
   "set_only_once": 0, 
   "unique": 0
  }, 
  {
   "allow_bulk_edit": 0, 
   "allow_on_submit": 0, 
   "bold": 0, 
   "collapsible": 0, 
   "columns": 0, 
   "fieldname": "jeevamrutham", 
   "fieldtype": "Float", 
   "hidden": 0, 
   "ignore_user_permissions": 0, 
   "ignore_xss_filter": 0, 
   "in_filter": 0, 
   "in_global_search": 0, 
   "in_list_view": 0, 
   "in_standard_filter": 0, 
   "label": "Jeevamrutham", 
   "length": 0, 
   "no_copy": 0, 
   "permlevel": 0, 
   "precision": "2", 
   "print_hide": 0, 
   "print_hide_if_no_value": 0, 
   "read_only": 0, 
   "remember_last_selected_value": 0, 
   "report_hide": 0, 
   "reqd": 0, 
   "search_index": 0, 
   "set_only_once": 0, 
   "unique": 0
  }, 
  {
   "allow_bulk_edit": 0, 
   "allow_on_submit": 0, 
   "bold": 0, 
   "collapsible": 0, 
   "columns": 0, 
   "fieldname": "tank_silt", 
   "fieldtype": "Float", 
   "hidden": 0, 
   "ignore_user_permissions": 0, 
   "ignore_xss_filter": 0, 
   "in_filter": 0, 
   "in_global_search": 0, 
   "in_list_view": 0, 
   "in_standard_filter": 0, 
   "label": "Tank Silt", 
   "length": 0, 
   "no_copy": 0, 
   "permlevel": 0, 
   "precision": "2", 
   "print_hide": 0, 
   "print_hide_if_no_value": 0, 
   "read_only": 0, 
   "remember_last_selected_value": 0, 
   "report_hide": 0, 
   "reqd": 0, 
   "search_index": 0, 
   "set_only_once": 0, 
   "unique": 0
  }, 
  {
   "allow_bulk_edit": 0, 
   "allow_on_submit": 0, 
   "bold": 0, 
   "collapsible": 0, 
   "columns": 0, 
   "fieldname": "fertilizers_and_manures_total", 
   "fieldtype": "Float", 
   "hidden": 0, 
   "ignore_user_permissions": 0, 
   "ignore_xss_filter": 0, 
   "in_filter": 0, 
   "in_global_search": 0, 
   "in_list_view": 0, 
   "in_standard_filter": 0, 
   "label": "Fertilizers and Manures Total", 
   "length": 0, 
   "no_copy": 0, 
   "permlevel": 0, 
   "precision": "2", 
   "print_hide": 0, 
   "print_hide_if_no_value": 0, 
   "read_only": 1, 
   "remember_last_selected_value": 0, 
   "report_hide": 0, 
   "reqd": 0, 
   "search_index": 0, 
   "set_only_once": 0, 
   "unique": 0
  }, 
  {
   "allow_bulk_edit": 0, 
   "allow_on_submit": 0, 
   "bold": 0, 
   "collapsible": 0, 
   "columns": 0, 
   "fieldname": "other_inputs", 
   "fieldtype": "Section Break", 
   "hidden": 0, 
   "ignore_user_permissions": 0, 
   "ignore_xss_filter": 0, 
   "in_filter": 0, 
   "in_global_search": 0, 
   "in_list_view": 0, 
   "in_standard_filter": 0, 
   "label": "Other Inputs", 
   "length": 0, 
   "no_copy": 0, 
   "permlevel": 0, 
   "precision": "", 
   "print_hide": 0, 
   "print_hide_if_no_value": 0, 
   "read_only": 0, 
   "remember_last_selected_value": 0, 
   "report_hide": 0, 
   "reqd": 0, 
   "search_index": 0, 
   "set_only_once": 0, 
   "unique": 0
  }, 
  {
   "allow_bulk_edit": 0, 
   "allow_on_submit": 0, 
   "bold": 0, 
   "collapsible": 0, 
   "columns": 0, 
   "fieldname": "insecticides", 
   "fieldtype": "Float", 
   "hidden": 0, 
   "ignore_user_permissions": 0, 
   "ignore_xss_filter": 0, 
   "in_filter": 0, 
   "in_global_search": 0, 
   "in_list_view": 0, 
   "in_standard_filter": 0, 
   "label": "Insecticides", 
   "length": 0, 
   "no_copy": 0, 
   "permlevel": 0, 
   "precision": "2", 
   "print_hide": 0, 
   "print_hide_if_no_value": 0, 
   "read_only": 0, 
   "remember_last_selected_value": 0, 
   "report_hide": 0, 
   "reqd": 0, 
   "search_index": 0, 
   "set_only_once": 0, 
   "unique": 0
  }, 
  {
   "allow_bulk_edit": 0, 
   "allow_on_submit": 0, 
   "bold": 0, 
   "collapsible": 0, 
   "columns": 0, 
   "fieldname": "weedicides", 
   "fieldtype": "Float", 
   "hidden": 0, 
   "ignore_user_permissions": 0, 
   "ignore_xss_filter": 0, 
   "in_filter": 0, 
   "in_global_search": 0, 
   "in_list_view": 0, 
   "in_standard_filter": 0, 
   "label": "Weedicides", 
   "length": 0, 
   "no_copy": 0, 
   "permlevel": 0, 
   "precision": "2", 
   "print_hide": 0, 
   "print_hide_if_no_value": 0, 
   "read_only": 0, 
   "remember_last_selected_value": 0, 
   "report_hide": 0, 
   "reqd": 0, 
   "search_index": 0, 
   "set_only_once": 0, 
   "unique": 0
  }, 
  {
   "allow_bulk_edit": 0, 
   "allow_on_submit": 0, 
   "bold": 0, 
   "collapsible": 0, 
   "columns": 0, 
   "fieldname": "misc_charges", 
   "fieldtype": "Float", 
   "hidden": 0, 
   "ignore_user_permissions": 0, 
   "ignore_xss_filter": 0, 
   "in_filter": 0, 
   "in_global_search": 0, 
   "in_list_view": 0, 
   "in_standard_filter": 0, 
   "label": "Misc Charges", 
   "length": 0, 
   "no_copy": 0, 
   "permlevel": 0, 
   "precision": "2", 
   "print_hide": 0, 
   "print_hide_if_no_value": 0, 
   "read_only": 0, 
   "remember_last_selected_value": 0, 
   "report_hide": 0, 
   "reqd": 0, 
   "search_index": 0, 
   "set_only_once": 0, 
   "unique": 0
  }, 
  {
   "allow_bulk_edit": 0, 
   "allow_on_submit": 0, 
   "bold": 0, 
   "collapsible": 0, 
   "columns": 0, 
   "fieldname": "column_break_32", 
   "fieldtype": "Column Break", 
   "hidden": 0, 
   "ignore_user_permissions": 0, 
   "ignore_xss_filter": 0, 
   "in_filter": 0, 
   "in_global_search": 0, 
   "in_list_view": 0, 
   "in_standard_filter": 0, 
   "length": 0, 
   "no_copy": 0, 
   "permlevel": 0, 
   "precision": "", 
   "print_hide": 0, 
   "print_hide_if_no_value": 0, 
   "read_only": 0, 
   "remember_last_selected_value": 0, 
   "report_hide": 0, 
   "reqd": 0, 
   "search_index": 0, 
   "set_only_once": 0, 
   "unique": 0
  }, 
  {
   "allow_bulk_edit": 0, 
   "allow_on_submit": 0, 
   "bold": 0, 
   "collapsible": 0, 
   "columns": 0, 
   "description": "(Bore-well/Motor Repair)", 
   "fieldname": "irrigation_charges", 
   "fieldtype": "Float", 
   "hidden": 0, 
   "ignore_user_permissions": 0, 
   "ignore_xss_filter": 0, 
   "in_filter": 0, 
   "in_global_search": 0, 
   "in_list_view": 0, 
   "in_standard_filter": 0, 
   "label": "Irrigation Charges ", 
   "length": 0, 
   "no_copy": 0, 
   "permlevel": 0, 
   "precision": "2", 
   "print_hide": 0, 
   "print_hide_if_no_value": 0, 
   "read_only": 0, 
   "remember_last_selected_value": 0, 
   "report_hide": 0, 
   "reqd": 0, 
   "search_index": 0, 
   "set_only_once": 0, 
   "unique": 0
  }, 
  {
   "allow_bulk_edit": 0, 
   "allow_on_submit": 0, 
   "bold": 0, 
   "collapsible": 0, 
   "columns": 0, 
   "fieldname": "interest_on_working_capital", 
   "fieldtype": "Float", 
   "hidden": 0, 
   "ignore_user_permissions": 0, 
   "ignore_xss_filter": 0, 
   "in_filter": 0, 
   "in_global_search": 0, 
   "in_list_view": 0, 
   "in_standard_filter": 0, 
   "label": "Interest on Working Capital", 
   "length": 0, 
   "no_copy": 0, 
   "permlevel": 0, 
   "precision": "2", 
   "print_hide": 0, 
   "print_hide_if_no_value": 0, 
   "read_only": 0, 
   "remember_last_selected_value": 0, 
   "report_hide": 0, 
   "reqd": 0, 
   "search_index": 0, 
   "set_only_once": 0, 
   "unique": 0
  }, 
  {
   "allow_bulk_edit": 0, 
   "allow_on_submit": 0, 
   "bold": 0, 
   "collapsible": 0, 
   "columns": 0, 
   "fieldname": "biopesticides_and_pheremone_traps", 
   "fieldtype": "Float", 
   "hidden": 0, 
   "ignore_user_permissions": 0, 
   "ignore_xss_filter": 0, 
   "in_filter": 0, 
   "in_global_search": 0, 
   "in_list_view": 0, 
   "in_standard_filter": 0, 
   "label": "Biopesticides and Pheremone Traps", 
   "length": 0, 
   "no_copy": 0, 
   "permlevel": 0, 
   "precision": "2", 
   "print_hide": 0, 
   "print_hide_if_no_value": 0, 
   "read_only": 0, 
   "remember_last_selected_value": 0, 
   "report_hide": 0, 
   "reqd": 0, 
   "search_index": 0, 
   "set_only_once": 0, 
   "unique": 0
  }, 
  {
   "allow_bulk_edit": 0, 
   "allow_on_submit": 0, 
   "bold": 0, 
   "collapsible": 0, 
   "columns": 0, 
   "fieldname": "other_inputs_total", 
   "fieldtype": "Float", 
   "hidden": 0, 
   "ignore_user_permissions": 0, 
   "ignore_xss_filter": 0, 
   "in_filter": 0, 
   "in_global_search": 0, 
   "in_list_view": 0, 
   "in_standard_filter": 0, 
   "label": "Other Inputs Total", 
   "length": 0, 
   "no_copy": 0, 
   "permlevel": 0, 
   "precision": "2", 
   "print_hide": 0, 
   "print_hide_if_no_value": 0, 
   "read_only": 1, 
   "remember_last_selected_value": 0, 
   "report_hide": 0, 
   "reqd": 0, 
   "search_index": 0, 
   "set_only_once": 0, 
   "unique": 0
  }, 
  {
   "allow_bulk_edit": 0, 
   "allow_on_submit": 0, 
   "bold": 0, 
   "collapsible": 0, 
   "columns": 0, 
   "fieldname": "fixed_cost", 
   "fieldtype": "Section Break", 
   "hidden": 0, 
   "ignore_user_permissions": 0, 
   "ignore_xss_filter": 0, 
   "in_filter": 0, 
   "in_global_search": 0, 
   "in_list_view": 0, 
   "in_standard_filter": 0, 
   "label": "Fixed Cost", 
   "length": 0, 
   "no_copy": 0, 
   "permlevel": 0, 
   "precision": "", 
   "print_hide": 0, 
   "print_hide_if_no_value": 0, 
   "read_only": 0, 
   "remember_last_selected_value": 0, 
   "report_hide": 0, 
   "reqd": 0, 
   "search_index": 0, 
   "set_only_once": 0, 
   "unique": 0
  }, 
  {
   "allow_bulk_edit": 0, 
   "allow_on_submit": 0, 
   "bold": 0, 
   "collapsible": 0, 
   "columns": 0, 
   "fieldname": "rental_value_of_own_land", 
   "fieldtype": "Float", 
   "hidden": 0, 
   "ignore_user_permissions": 0, 
   "ignore_xss_filter": 0, 
   "in_filter": 0, 
   "in_global_search": 0, 
   "in_list_view": 0, 
   "in_standard_filter": 0, 
   "label": "Rental Value of Own Land", 
   "length": 0, 
   "no_copy": 0, 
   "permlevel": 0, 
   "precision": "2", 
   "print_hide": 0, 
   "print_hide_if_no_value": 0, 
   "read_only": 0, 
   "remember_last_selected_value": 0, 
   "report_hide": 0, 
   "reqd": 0, 
   "search_index": 0, 
   "set_only_once": 0, 
   "unique": 0
  }, 
  {
   "allow_bulk_edit": 0, 
   "allow_on_submit": 0, 
   "bold": 0, 
   "collapsible": 0, 
   "columns": 0, 
   "fieldname": "rent_paid_for_leased_in_land", 
   "fieldtype": "Float", 
   "hidden": 0, 
   "ignore_user_permissions": 0, 
   "ignore_xss_filter": 0, 
   "in_filter": 0, 
   "in_global_search": 0, 
   "in_list_view": 0, 
   "in_standard_filter": 0, 
   "label": "Rent Paid for Leased In Land", 
   "length": 0, 
   "no_copy": 0, 
   "permlevel": 0, 
   "precision": "2", 
   "print_hide": 0, 
   "print_hide_if_no_value": 0, 
   "read_only": 0, 
   "remember_last_selected_value": 0, 
   "report_hide": 0, 
   "reqd": 0, 
   "search_index": 0, 
   "set_only_once": 0, 
   "unique": 0
  }, 
  {
   "allow_bulk_edit": 0, 
   "allow_on_submit": 0, 
   "bold": 0, 
   "collapsible": 0, 
   "columns": 0, 
   "fieldname": "land_revenue_and_taxes", 
   "fieldtype": "Float", 
   "hidden": 0, 
   "ignore_user_permissions": 0, 
   "ignore_xss_filter": 0, 
   "in_filter": 0, 
   "in_global_search": 0, 
   "in_list_view": 0, 
   "in_standard_filter": 0, 
   "label": "Land Revenue and Taxes", 
   "length": 0, 
   "no_copy": 0, 
   "permlevel": 0, 
   "precision": "2", 
   "print_hide": 0, 
   "print_hide_if_no_value": 0, 
   "read_only": 0, 
   "remember_last_selected_value": 0, 
   "report_hide": 0, 
   "reqd": 0, 
   "search_index": 0, 
   "set_only_once": 0, 
   "unique": 0
  }, 
  {
   "allow_bulk_edit": 0, 
   "allow_on_submit": 0, 
   "bold": 0, 
   "collapsible": 0, 
   "columns": 0, 
   "fieldname": "column_break_41", 
   "fieldtype": "Column Break", 
   "hidden": 0, 
   "ignore_user_permissions": 0, 
   "ignore_xss_filter": 0, 
   "in_filter": 0, 
   "in_global_search": 0, 
   "in_list_view": 0, 
   "in_standard_filter": 0, 
   "length": 0, 
   "no_copy": 0, 
   "permlevel": 0, 
   "precision": "", 
   "print_hide": 0, 
   "print_hide_if_no_value": 0, 
   "read_only": 0, 
   "remember_last_selected_value": 0, 
   "report_hide": 0, 
   "reqd": 0, 
   "search_index": 0, 
   "set_only_once": 0, 
   "unique": 0
  }, 
  {
   "allow_bulk_edit": 0, 
   "allow_on_submit": 0, 
   "bold": 0, 
   "collapsible": 0, 
   "columns": 0, 
   "fieldname": "interest_on_fixed_capital", 
   "fieldtype": "Float", 
   "hidden": 0, 
   "ignore_user_permissions": 0, 
   "ignore_xss_filter": 0, 
   "in_filter": 0, 
   "in_global_search": 0, 
   "in_list_view": 0, 
   "in_standard_filter": 0, 
   "label": "Interest on Fixed Capital", 
   "length": 0, 
   "no_copy": 0, 
   "permlevel": 0, 
   "precision": "2", 
   "print_hide": 0, 
   "print_hide_if_no_value": 0, 
   "read_only": 0, 
   "remember_last_selected_value": 0, 
   "report_hide": 0, 
   "reqd": 0, 
   "search_index": 0, 
   "set_only_once": 0, 
   "unique": 0
  }, 
  {
   "allow_bulk_edit": 0, 
   "allow_on_submit": 0, 
   "bold": 0, 
   "collapsible": 0, 
   "columns": 0, 
   "fieldname": "depreciation_on_implements_and_farm_buildings", 
   "fieldtype": "Float", 
   "hidden": 0, 
   "ignore_user_permissions": 0, 
   "ignore_xss_filter": 0, 
   "in_filter": 0, 
   "in_global_search": 0, 
   "in_list_view": 0, 
   "in_standard_filter": 0, 
   "label": "Depreciation on Implements and Farm Buildings", 
   "length": 0, 
   "no_copy": 0, 
   "permlevel": 0, 
   "precision": "2", 
   "print_hide": 0, 
   "print_hide_if_no_value": 0, 
   "read_only": 0, 
   "remember_last_selected_value": 0, 
   "report_hide": 0, 
   "reqd": 0, 
   "search_index": 0, 
   "set_only_once": 0, 
   "unique": 0
  }, 
  {
   "allow_bulk_edit": 0, 
   "allow_on_submit": 0, 
   "bold": 0, 
   "collapsible": 0, 
   "columns": 0, 
   "fieldname": "fixed_cost_total", 
   "fieldtype": "Float", 
   "hidden": 0, 
   "ignore_user_permissions": 0, 
   "ignore_xss_filter": 0, 
   "in_filter": 0, 
   "in_global_search": 0, 
   "in_list_view": 0, 
   "in_standard_filter": 0, 
   "label": "Fixed Cost Total", 
   "length": 0, 
   "no_copy": 0, 
   "permlevel": 0, 
   "precision": "2", 
   "print_hide": 0, 
   "print_hide_if_no_value": 0, 
   "read_only": 1, 
   "remember_last_selected_value": 0, 
   "report_hide": 0, 
   "reqd": 0, 
   "search_index": 0, 
   "set_only_once": 0, 
   "unique": 0
  }, 
  {
   "allow_bulk_edit": 0, 
   "allow_on_submit": 0, 
   "bold": 0, 
   "collapsible": 0, 
   "columns": 0, 
   "fieldname": "other_costs", 
   "fieldtype": "Section Break", 
   "hidden": 0, 
   "ignore_user_permissions": 0, 
   "ignore_xss_filter": 0, 
   "in_filter": 0, 
   "in_global_search": 0, 
   "in_list_view": 0, 
   "in_standard_filter": 0, 
   "label": "Other Costs", 
   "length": 0, 
   "no_copy": 0, 
   "permlevel": 0, 
   "precision": "", 
   "print_hide": 0, 
   "print_hide_if_no_value": 0, 
   "read_only": 0, 
   "remember_last_selected_value": 0, 
   "report_hide": 0, 
   "reqd": 0, 
   "search_index": 0, 
   "set_only_once": 0, 
   "unique": 0
  }, 
  {
   "allow_bulk_edit": 0, 
   "allow_on_submit": 0, 
   "bold": 0, 
   "collapsible": 0, 
   "columns": 0, 
   "fieldname": "crop_insurance_premium", 
   "fieldtype": "Float", 
   "hidden": 0, 
   "ignore_user_permissions": 0, 
   "ignore_xss_filter": 0, 
   "in_filter": 0, 
   "in_global_search": 0, 
   "in_list_view": 0, 
   "in_standard_filter": 0, 
   "label": "Crop Insurance Premium", 
   "length": 0, 
   "no_copy": 0, 
   "permlevel": 0, 
   "precision": "2", 
   "print_hide": 0, 
   "print_hide_if_no_value": 0, 
   "read_only": 0, 
   "remember_last_selected_value": 0, 
   "report_hide": 0, 
   "reqd": 0, 
   "search_index": 0, 
   "set_only_once": 0, 
   "unique": 0
  }, 
  {
   "allow_bulk_edit": 0, 
   "allow_on_submit": 0, 
   "bold": 0, 
   "collapsible": 0, 
   "columns": 0, 
   "fieldname": "marketing_costs", 
   "fieldtype": "Float", 
   "hidden": 0, 
   "ignore_user_permissions": 0, 
   "ignore_xss_filter": 0, 
   "in_filter": 0, 
   "in_global_search": 0, 
   "in_list_view": 0, 
   "in_standard_filter": 0, 
   "label": "Marketing Costs", 
   "length": 0, 
   "no_copy": 0, 
   "permlevel": 0, 
   "precision": "2", 
   "print_hide": 0, 
   "print_hide_if_no_value": 0, 
   "read_only": 0, 
   "remember_last_selected_value": 0, 
   "report_hide": 0, 
   "reqd": 0, 
   "search_index": 0, 
   "set_only_once": 0, 
   "unique": 0
  }, 
  {
   "allow_bulk_edit": 0, 
   "allow_on_submit": 0, 
   "bold": 0, 
   "collapsible": 0, 
   "columns": 0, 
   "fieldname": "column_break_48", 
   "fieldtype": "Column Break", 
   "hidden": 0, 
   "ignore_user_permissions": 0, 
   "ignore_xss_filter": 0, 
   "in_filter": 0, 
   "in_global_search": 0, 
   "in_list_view": 0, 
   "in_standard_filter": 0, 
   "length": 0, 
   "no_copy": 0, 
   "permlevel": 0, 
   "precision": "", 
   "print_hide": 0, 
   "print_hide_if_no_value": 0, 
   "read_only": 0, 
   "remember_last_selected_value": 0, 
   "report_hide": 0, 
   "reqd": 0, 
   "search_index": 0, 
   "set_only_once": 0, 
   "unique": 0
  }, 
  {
   "allow_bulk_edit": 0, 
   "allow_on_submit": 0, 
   "bold": 0, 
   "collapsible": 0, 
   "columns": 0, 
   "fieldname": "transport_costs", 
   "fieldtype": "Float", 
   "hidden": 0, 
   "ignore_user_permissions": 0, 
   "ignore_xss_filter": 0, 
   "in_filter": 0, 
   "in_global_search": 0, 
   "in_list_view": 0, 
   "in_standard_filter": 0, 
   "label": "Transport Costs", 
   "length": 0, 
   "no_copy": 0, 
   "permlevel": 0, 
   "precision": "2", 
   "print_hide": 0, 
   "print_hide_if_no_value": 0, 
   "read_only": 0, 
   "remember_last_selected_value": 0, 
   "report_hide": 0, 
   "reqd": 0, 
   "search_index": 0, 
   "set_only_once": 0, 
   "unique": 0
  }, 
  {
   "allow_bulk_edit": 0, 
   "allow_on_submit": 0, 
   "bold": 0, 
   "collapsible": 0, 
   "columns": 0, 
   "fieldname": "purchases_of_farm_machinery_and_implements", 
   "fieldtype": "Float", 
   "hidden": 0, 
   "ignore_user_permissions": 0, 
   "ignore_xss_filter": 0, 
   "in_filter": 0, 
   "in_global_search": 0, 
   "in_list_view": 0, 
   "in_standard_filter": 0, 
   "label": "Purchases of Farm Machinery and Implements", 
   "length": 0, 
   "no_copy": 0, 
   "permlevel": 0, 
   "precision": "2", 
   "print_hide": 0, 
   "print_hide_if_no_value": 0, 
   "read_only": 0, 
   "remember_last_selected_value": 0, 
   "report_hide": 0, 
   "reqd": 0, 
   "search_index": 0, 
   "set_only_once": 0, 
   "unique": 0
  }, 
  {
   "allow_bulk_edit": 0, 
   "allow_on_submit": 0, 
   "bold": 0, 
   "collapsible": 0, 
   "columns": 0, 
   "fieldname": "other_costs_total", 
   "fieldtype": "Float", 
   "hidden": 0, 
   "ignore_user_permissions": 0, 
   "ignore_xss_filter": 0, 
   "in_filter": 0, 
   "in_global_search": 0, 
   "in_list_view": 0, 
   "in_standard_filter": 0, 
   "label": "Other Costs Total", 
   "length": 0, 
   "no_copy": 0, 
   "permlevel": 0, 
   "precision": "2", 
   "print_hide": 0, 
   "print_hide_if_no_value": 0, 
   "read_only": 1, 
   "remember_last_selected_value": 0, 
   "report_hide": 0, 
   "reqd": 0, 
   "search_index": 0, 
   "set_only_once": 0, 
   "unique": 0
  }, 
  {
   "allow_bulk_edit": 0, 
   "allow_on_submit": 0, 
   "bold": 0, 
   "collapsible": 0, 
   "columns": 0, 
   "fieldname": "cost_of_cultivation", 
   "fieldtype": "Section Break", 
   "hidden": 0, 
   "ignore_user_permissions": 0, 
   "ignore_xss_filter": 0, 
   "in_filter": 0, 
   "in_global_search": 0, 
   "in_list_view": 0, 
   "in_standard_filter": 0, 
   "label": "Cost of Cultivation", 
   "length": 0, 
   "no_copy": 1, 
   "options": "", 
   "permlevel": 0, 
   "print_hide": 1, 
   "print_hide_if_no_value": 0, 
   "read_only": 1, 
   "remember_last_selected_value": 0, 
   "report_hide": 0, 
   "reqd": 0, 
   "search_index": 0, 
   "set_only_once": 0, 
   "unique": 0
  }, 
  {
   "allow_bulk_edit": 0, 
   "allow_on_submit": 0, 
   "bold": 0, 
   "collapsible": 0, 
   "columns": 0, 
   "fieldname": "total_cultivation_of_cost", 
   "fieldtype": "Float", 
   "hidden": 0, 
   "ignore_user_permissions": 0, 
   "ignore_xss_filter": 0, 
   "in_filter": 0, 
   "in_global_search": 0, 
   "in_list_view": 1, 
   "in_standard_filter": 0, 
   "label": "Total Cultivation of Cost ", 
   "length": 0, 
   "no_copy": 0, 
   "permlevel": 0, 
   "precision": "2", 
   "print_hide": 0, 
   "print_hide_if_no_value": 0, 
   "read_only": 1, 
   "remember_last_selected_value": 0, 
   "report_hide": 0, 
   "reqd": 0, 
   "search_index": 0, 
   "set_only_once": 0, 
   "unique": 0
  }, 
  {
   "allow_bulk_edit": 0, 
   "allow_on_submit": 0, 
   "bold": 0, 
   "collapsible": 0, 
   "columns": 0, 
   "fieldname": "amended_from", 
   "fieldtype": "Link", 
   "hidden": 0, 
   "ignore_user_permissions": 0, 
   "ignore_xss_filter": 0, 
   "in_filter": 0, 
   "in_global_search": 0, 
   "in_list_view": 0, 
   "in_standard_filter": 0, 
   "label": "Amended From", 
   "length": 0, 
   "no_copy": 1, 
   "options": "Cost of Cultivation", 
   "permlevel": 0, 
   "print_hide": 1, 
   "print_hide_if_no_value": 0, 
   "read_only": 1, 
   "remember_last_selected_value": 0, 
   "report_hide": 0, 
   "reqd": 0, 
   "search_index": 0, 
   "set_only_once": 0, 
   "unique": 0
  }
 ], 
 "has_web_view": 0, 
 "hide_heading": 0, 
 "hide_toolbar": 0, 
 "idx": 0, 
 "image_view": 0, 
 "in_create": 0, 
 "is_submittable": 0, 
 "issingle": 0, 
 "istable": 0, 
 "max_attachments": 0, 
 "modified": "2019-01-23 13:25:12.085843", 
 "modified_by": "Administrator", 
 "module": "FPO Management", 
 "name": "Cost of Cultivation", 
 "name_case": "Title Case", 
 "owner": "prasanna@csa-india.org", 
 "permissions": [
  {
   "amend": 0, 
   "apply_user_permissions": 0, 
   "cancel": 0, 
   "create": 1, 
   "delete": 1, 
   "email": 1, 
   "export": 1, 
   "if_owner": 0, 
   "import": 0, 
   "permlevel": 0, 
   "print": 1, 
   "read": 1, 
   "report": 1, 
   "role": "System Manager", 
   "set_user_permissions": 0, 
   "share": 1, 
   "submit": 0, 
   "write": 1
  }, 
  {
   "amend": 0, 
   "apply_user_permissions": 0, 
   "cancel": 0, 
   "create": 1, 
   "delete": 1, 
   "email": 1, 
   "export": 1, 
   "if_owner": 0, 
   "import": 0, 
   "permlevel": 0, 
   "print": 1, 
   "read": 1, 
   "report": 1, 
   "role": "FPO User", 
   "set_user_permissions": 0, 
   "share": 1, 
   "submit": 0, 
   "write": 1
  }
 ], 
 "quick_entry": 0, 
 "read_only": 0, 
 "read_only_onload": 0, 
 "search_fields": "", 
 "show_name_in_global_search": 0, 
 "sort_field": "modified", 
 "sort_order": "DESC", 
 "title_field": "", 
 "track_changes": 1, 
 "track_seen": 0
}